database_wrapper_redis/__init__.py
database_wrapper_redis/connector.py
database_wrapper_redis/py.typed
database_wrapper_redis-0.2.23.dist-info/METADATA
database_wrapper_redis-0.2.23.dist-info/WHEEL
database_wrapper_redis-0.2.23.dist-info/top_level.txt
database_wrapper_redis-0.2.23.dist-info/RECORD
